testpoetrypypi/__init__.py
testpoetrypypi/hello.py
testpoetrypypi-0.1.29.dist-info/entry_points.txt
testpoetrypypi-0.1.29.dist-info/WHEEL
testpoetrypypi-0.1.29.dist-info/METADATA
testpoetrypypi-0.1.29.dist-info/RECORD
