Metadata-Version: 2.1
Name: testpoetrypypi
Version: 0.1.29
Summary: 
License: Apache-2.0
Author: Jeff
Requires-Python: >=3.7,<4.0
Classifier: License :: OSI Approved :: Apache Software License
Classifier: Programming Language :: Python :: 3
Classifier: Programming Language :: Python :: 3.7
Classifier: Programming Language :: Python :: 3.8
Requires-Dist: poetry-version (>=0.1.5,<0.2.0)
